setup.py
Gaussian_and_Binomial_Distribution/Binomialdistribution.py
Gaussian_and_Binomial_Distribution/Gaussiandistribution.py
Gaussian_and_Binomial_Distribution/Generaldistribution.py
Gaussian_and_Binomial_Distribution/__init__.py
Gaussian_and_Binomial_Distribution.egg-info/PKG-INFO
Gaussian_and_Binomial_Distribution.egg-info/SOURCES.txt
Gaussian_and_Binomial_Distribution.egg-info/dependency_links.txt
Gaussian_and_Binomial_Distribution.egg-info/not-zip-safe
Gaussian_and_Binomial_Distribution.egg-info/top_level.txt